s3_pypi_proxy/__init__.py
s3_pypi_proxy/s3.py
s3_pypi_proxy-0.0.2.dist-info/entry_points.txt
s3_pypi_proxy-0.0.2.dist-info/LICENSE
s3_pypi_proxy-0.0.2.dist-info/WHEEL
s3_pypi_proxy-0.0.2.dist-info/METADATA
s3_pypi_proxy-0.0.2.dist-info/RECORD
