Metadata-Version: 2.1
Name: s3-pypi-proxy
Version: 0.0.2
Summary: Turn an S3 bucket into a PyPI repo
License: MIT
Author: Josh Bode
Author-email: joshbode@fastmail.com
Requires-Python: >=3.8
Classifier: License :: OSI Approved :: MIT License
Classifier: Programming Language :: Python :: 3
Classifier: Programming Language :: Python :: 3.10
Classifier: Programming Language :: Python :: 3.8
Classifier: Programming Language :: Python :: 3.9
Requires-Dist: Flask (>=2.1.2,<3.0.0)
Requires-Dist: boto3 (>=1.22.6,<2.0.0)
Requires-Dist: structlog (>=21.5.0,<22.0.0)
